src/__init__.py
src/configs.py
src/main.py
src/metrics.py
src/plot_utils.py
src/utils.py
src/core/__init__.py
src/core/bert/__init__.py
src/core/bert/bert.py
src/core/bert/dataset_finetune.py
src/core/bert/dataset_pretrain.py
src/core/bert/finetune.py
src/core/bert/model.py
src/core/bert/pretrain.py
src/core/bow/__init__.py
src/core/bow/bow.py
src/core/glove/__init__.py
src/core/glove/dataset.py
src/core/glove/glove.py
src/core/glove/model.py
src/core/gpt/__init__.py
src/core/gpt/dataset.py
src/core/gpt/gpt.py
src/core/gpt/model.py
src/core/gru/__init__.py
src/core/gru/dataset.py
src/core/gru/gru.py
src/core/gru/model.py
src/core/hmm/__init__.py
src/core/hmm/hmm.py
src/core/lstm/__init__.py
src/core/lstm/dataset.py
src/core/lstm/lstm.py
src/core/lstm/model.py
src/core/ngram/__init__.py
src/core/ngram/ngram.py
src/core/rnn/__init__.py
src/core/rnn/dataset.py
src/core/rnn/model.py
src/core/rnn/rnn.py
src/core/seq2seq/__init__.py
src/core/seq2seq/dataset.py
src/core/seq2seq/model.py
src/core/seq2seq/seq2seq.py
src/core/tfidf/__init__.py
src/core/tfidf/tfidf.py
src/core/transformer/__init__.py
src/core/transformer/dataset.py
src/core/transformer/model.py
src/core/transformer/transformer.py
src/core/word2vec/__init__.py
src/core/word2vec/dataset.py
src/core/word2vec/huffman.py
src/core/word2vec/model.py
src/core/word2vec/word2vec.py
src/preprocess/__init__.py
src/preprocess/eng2tel.py
src/preprocess/flickr.py
src/preprocess/imdb_reviews.py
src/preprocess/pos.py
src/preprocess/utils.py
ScratchNLP-1.0.0.dist-info/LICENSE
ScratchNLP-1.0.0.dist-info/METADATA
ScratchNLP-1.0.0.dist-info/WHEEL
ScratchNLP-1.0.0.dist-info/entry_points.txt
ScratchNLP-1.0.0.dist-info/top_level.txt
ScratchNLP-1.0.0.dist-info/RECORD
