Metadata-Version: 2.1
Name: ScratchNLP
Version: 1.0.0
Summary: Library with NLP Algorithms implemented from scratch
Home-page: https://github.com/shanmukh05/scratch_nlp
Author: Shanmukha Sainath
Author-email: Shanmukha Sainath <venkatashanmukhasainathg@gmail.com>
Project-URL: Homepage, https://github.com/shanmukh05/scratch_nlp
Project-URL: Bug Tracker, https://github.com/shanmukh05/scratch_nlp/issues
Project-URL: Documentation, https://shanmukh05.github.io/scratch_nlp/
Project-URL: Source Code, https://github.com/shanmukh05/scratch_nlp
Keywords: NLP,Implementation,Machine Learning
Classifier: Programming Language :: Python :: 3
Classifier: License :: OSI Approved :: MIT License
Classifier: Operating System :: OS Independent
Requires-Python: >=3.12
License-File: LICENSE
Provides-Extra: dev
Requires-Dist: black; extra == "dev"
